test/__init__.py
test/mock_client.py
test/save_api_requests_responses.py
test/test_access.py
test/test_ebet_betting.py
veikkaaja/__init__.py
veikkaaja/endpoints.py
veikkaaja/responses.py
veikkaaja/types.py
veikkaaja/veikkaus_client.py
veikkaaja-0.1.3.dist-info/LICENSE
veikkaaja-0.1.3.dist-info/METADATA
veikkaaja-0.1.3.dist-info/WHEEL
veikkaaja-0.1.3.dist-info/entry_points.txt
veikkaaja-0.1.3.dist-info/top_level.txt
veikkaaja-0.1.3.dist-info/RECORD
