Metadata-Version: 2.1
Name: veikkaaja
Version: 0.1.3
Summary: A wrapper for Veikkaus (veikkaus.fi) betting API.
Home-page: https://github.com/miikama/veikkaaja
Author: Miika Mäkelä
Author-email: makelanmiika@gmail.com
License: UNKNOWN
Platform: UNKNOWN
Classifier: Programming Language :: Python :: 3
Classifier: License :: OSI Approved :: MIT License
Classifier: Operating System :: OS Independent
Requires-Python: >=3.6
License-File: LICENSE
Requires-Dist: requests
Provides-Extra: dev
Requires-Dist: pytest ; extra == 'dev'
Requires-Dist: pylint ; extra == 'dev'
Requires-Dist: yapf ; extra == 'dev'
Requires-Dist: mypy ; extra == 'dev'
Requires-Dist: responses ; extra == 'dev'
Requires-Dist: twine ; extra == 'dev'
Requires-Dist: types-requests ; extra == 'dev'
